nlp_annotations/__init__.py
nlp_annotations-1.0.1.dist-info/METADATA
nlp_annotations-1.0.1.dist-info/WHEEL
nlp_annotations-1.0.1.dist-info/top_level.txt
nlp_annotations-1.0.1.dist-info/RECORD
