Metadata-Version: 2.1
Name: nlp-annotations
Version: 1.0.1
Summary: NLP Annotation Helpers
Home-page: https://github.com/asciialex/nlp-annotations
Author: asciialex
Author-email: alex@asciialex.com
License: UNKNOWN
Platform: UNKNOWN
Classifier: Programming Language :: Python :: 3
Classifier: License :: OSI Approved :: MIT License
Classifier: Operating System :: OS Independent
Requires-Python: >=3.6
